languagestatisticslibpy/Bigrams.py
languagestatisticslibpy/Grams.py
languagestatisticslibpy/GramsType.py
languagestatisticslibpy/Hexagrams.py
languagestatisticslibpy/LanguageStatistics.py
languagestatisticslibpy/LanguageStatisticsFile.py
languagestatisticslibpy/Node.py
languagestatisticslibpy/Pentagrams.py
languagestatisticslibpy/Tetragrams.py
languagestatisticslibpy/Trigrams.py
languagestatisticslibpy/Unigrams.py
languagestatisticslibpy/WordTree.py
languagestatisticslibpy/__init__.py
languagestatisticslibpy/test1.py
languagestatisticslibpy/test2.py
languagestatisticslibpy-1.0.3.dist-info/LICENSE
languagestatisticslibpy-1.0.3.dist-info/METADATA
languagestatisticslibpy-1.0.3.dist-info/WHEEL
languagestatisticslibpy-1.0.3.dist-info/RECORD
