Metadata-Version: 2.1
Name: LanguageStatisticsLibPy
Version: 1.0.3
Summary: Quick and robust Python functions to do cryptanalysis using language statistics data for 15 languages
License: Apache-2.0
Author: Nils Kopal and Bernhard Esslinger
Author-email: kopal@cryptool.org
Requires-Python: >=3.10,<4.0
Classifier: License :: OSI Approved :: Apache Software License
Classifier: Operating System :: OS Independent
Classifier: Programming Language :: Python :: 3
Classifier: Programming Language :: Python :: 3.10
Classifier: Programming Language :: Python :: 3.11
Classifier: Programming Language :: Python :: 3.12
Classifier: Programming Language :: Python :: 3.13
Project-URL: Homepage, https://github.com/CrypToolProject/LanguageStatisticsLibPy
